gpsfun/__init__.py
gpsfun/col.py
gpsfun/gpsfun.py
gpsfun/readers.py
gpsfun/tracks.py
gpsfun-0.0.1.dist-info/AUTHORS.rst
gpsfun-0.0.1.dist-info/LICENSE
gpsfun-0.0.1.dist-info/METADATA
gpsfun-0.0.1.dist-info/WHEEL
gpsfun-0.0.1.dist-info/top_level.txt
gpsfun-0.0.1.dist-info/RECORD
