Metadata-Version: 2.1
Name: gpsfun
Version: 0.0.1
Summary: Read and analyse gps activity, bike, run, data
Home-page: https://github.com/vincentdavis/gpsfun
Author: Vincent Davis
Author-email: vincent@heteroskedastic.com
License: MIT license
Keywords: gpsfun
Platform: UNKNOWN
Classifier: Development Status :: 2 - Pre-Alpha
Classifier: Intended Audience :: Developers
Classifier: License :: OSI Approved :: MIT License
Classifier: Natural Language :: English
Classifier: Programming Language :: Python :: 3
Classifier: Programming Language :: Python :: 3.6
Classifier: Programming Language :: Python :: 3.7
Classifier: Programming Language :: Python :: 3.8
Requires-Python: >=3.6
Requires-Dist: pandas
Requires-Dist: haversine
Requires-Dist: fitdecode
Requires-Dist: xmltodict
